preprocspectra/__init__.py
preprocspectra/transformation_tools/__init__.py
preprocspectra/transformation_tools/handle_transformations.py
preprocspectra/transformation_tools/transformations.py
preprocspectra/utils/__init__.py
preprocspectra/utils/average.py
preprocspectra-0.0.65.dist-info/LICENSE
preprocspectra-0.0.65.dist-info/METADATA
preprocspectra-0.0.65.dist-info/WHEEL
preprocspectra-0.0.65.dist-info/top_level.txt
preprocspectra-0.0.65.dist-info/RECORD
